edazer/__init__.py
edazer/core.py
edazer/profiling.py
edazer/utils/__init__.py
edazer/utils/idf.py
edazer/utils/pk.py
edazer-0.1.4.1.dist-info/licenses/LICENSE
edazer-0.1.4.1.dist-info/METADATA
edazer-0.1.4.1.dist-info/WHEEL
edazer-0.1.4.1.dist-info/top_level.txt
edazer-0.1.4.1.dist-info/RECORD
