Metadata-Version: 2.4
Name: edazer
Version: 0.1.4.1
Summary: lightweight library that provides functionalities for common EDA tasks
Author: Adarsh R
Author-email: 7adarsh9@gmail.com
Classifier: Programming Language :: Python :: 3
Classifier: License :: OSI Approved :: MIT License
Classifier: Operating System :: OS Independent
Requires-Python: >=3.6
License-File: LICENSE
Requires-Dist: pandas>=1.0.0
Requires-Dist: ipython>=7.0.0
Requires-Dist: polars>=0.19.0
Requires-Dist: pyarrow>=10.0.0
Requires-Dist: itables>=2.4.4
Requires-Dist: ydata_profiling>=4.16.1
Dynamic: author
Dynamic: author-email
Dynamic: classifier
Dynamic: description
Dynamic: description-content-type
Dynamic: license-file
Dynamic: requires-dist
Dynamic: requires-python
Dynamic: summary
